JavaWeixinKaifa/README.md
JavaWeixinKaifa/__init__.py
JavaWeixinKaifa/__main__.py
JavaWeixinKaifa/file.epub
JavaWeixinKaifa/index.html
JavaWeixinKaifa/css/__init__.py
JavaWeixinKaifa/css/annotations.css
JavaWeixinKaifa/css/main.css
JavaWeixinKaifa/css/normalize.css
JavaWeixinKaifa/css/popup.css
JavaWeixinKaifa/font/__init__.py
JavaWeixinKaifa/font/fontello.eot
JavaWeixinKaifa/font/fontello.svg
JavaWeixinKaifa/font/fontello.ttf
JavaWeixinKaifa/font/fontello.woff
JavaWeixinKaifa/img/__init__.py
JavaWeixinKaifa/img/annotator-glyph-sprite.png
JavaWeixinKaifa/img/annotator-icon-sprite.png
JavaWeixinKaifa/img/apple-touch-icon.png
JavaWeixinKaifa/img/cancelfullscreen.png
JavaWeixinKaifa/img/close.png
JavaWeixinKaifa/img/fullscreen.png
JavaWeixinKaifa/img/loader.gif
JavaWeixinKaifa/img/menu-icon.png
JavaWeixinKaifa/img/save.png
JavaWeixinKaifa/img/saved.png
JavaWeixinKaifa/img/settings-s.png
JavaWeixinKaifa/img/settings.png
JavaWeixinKaifa/img/star.png
JavaWeixinKaifa/js/__init__.py
JavaWeixinKaifa/js/epub.js
JavaWeixinKaifa/js/epub.min.js
JavaWeixinKaifa/js/epub.min.map
JavaWeixinKaifa/js/hooks.min.js
JavaWeixinKaifa/js/hooks.min.map
JavaWeixinKaifa/js/reader.js
JavaWeixinKaifa/js/reader.js.map
JavaWeixinKaifa/js/reader.min.js
JavaWeixinKaifa/js/reader.min.map
JavaWeixinKaifa/js/hooks/__init__.py
JavaWeixinKaifa/js/hooks/extensions/__init__.py
JavaWeixinKaifa/js/hooks/extensions/highlight.js
JavaWeixinKaifa/js/libs/__init__.py
JavaWeixinKaifa/js/libs/jquery.min.js
JavaWeixinKaifa/js/libs/localforage.min.js
JavaWeixinKaifa/js/libs/screenfull.js
JavaWeixinKaifa/js/libs/screenfull.min.js
JavaWeixinKaifa/js/libs/zip.min.js
JavaWeixinKaifa/js/plugins/__init__.py
JavaWeixinKaifa/js/plugins/hypothesis.js
JavaWeixinKaifa/js/plugins/search.js
java_weixin_kaifa-2024.3.3.0.dist-info/METADATA
java_weixin_kaifa-2024.3.3.0.dist-info/WHEEL
java_weixin_kaifa-2024.3.3.0.dist-info/entry_points.txt
java_weixin_kaifa-2024.3.3.0.dist-info/top_level.txt
java_weixin_kaifa-2024.3.3.0.dist-info/RECORD
